zafer/__init__.py
zafer/hasnain.py
zafer-0.1.0.dist-info/licenses/LICENSE
zafer-0.1.0.dist-info/METADATA
zafer-0.1.0.dist-info/WHEEL
zafer-0.1.0.dist-info/top_level.txt
zafer-0.1.0.dist-info/RECORD
